{
    "$schema": "https://marketplace.umbraco.com/umbraco-marketplace-schema.json",
    "AuthorDetails": {
      "Name": "Sebastian Falborg Braun",
      "ImageUrl": "https://github.com/SebastianFalborg.png"
    },
    "Category": "",
    "Description": "",
    "LicenseTypes": [ "Free" ],
    "IssueTrackerUrl": "https://github.com/SebastianFalborg/JobsJobsJobs/issues",
    "PackageType": "Package",
    "Tags": [],
    "Title": "Jobs Jobs Jobs ",
    "Screenshots": [
        {
            "ImageUrl": "https://raw.githubusercontent.com/SebastianFalborg/JobsJobsJobs/main/docs/Screenshots/dashboard-overview.png",
            "Caption": "Dashboard overview showing job status and recent runs"
        },
        {
            "ImageUrl": "https://raw.githubusercontent.com/SebastianFalborg/JobsJobsJobs/main/docs/Screenshots/history-tab.png",
            "Caption": "History tab with filtering and search across all job runs"
        },
        {
            "ImageUrl": "https://raw.githubusercontent.com/SebastianFalborg/JobsJobsJobs/main/docs/Screenshots/stoppable-cron-job.png",
            "Caption": "Stoppable CRON job with cooperative cancellation support"
        }
    ]
  }
